minfx/__init__.py
minfx/neptune_v3.py
minfx/neptune_v2/__init__.py
minfx/neptune_v2/constants.py
minfx/neptune_v2/envs.py
minfx/neptune_v2/exceptions.py
minfx/neptune_v2/handler.py
minfx/neptune_v2/progress_bar.py
minfx/neptune_v2/py.typed
minfx/neptune_v2/table.py
minfx/neptune_v2/typing.py
minfx/neptune_v2/utils.py
minfx/neptune_v2/version.py
minfx/neptune_v2/api/__init__.py
minfx/neptune_v2/api/dtos.py
minfx/neptune_v2/api/requests_utils.py
minfx/neptune_v2/api/searching_entries.py
minfx/neptune_v2/attributes/__init__.py
minfx/neptune_v2/attributes/attribute.py
minfx/neptune_v2/attributes/constants.py
minfx/neptune_v2/attributes/file_set.py
minfx/neptune_v2/attributes/namespace.py
minfx/neptune_v2/attributes/utils.py
minfx/neptune_v2/attributes/atoms/__init__.py
minfx/neptune_v2/attributes/atoms/artifact.py
minfx/neptune_v2/attributes/atoms/atom.py
minfx/neptune_v2/attributes/atoms/boolean.py
minfx/neptune_v2/attributes/atoms/copiable_atom.py
minfx/neptune_v2/attributes/atoms/datetime.py
minfx/neptune_v2/attributes/atoms/file.py
minfx/neptune_v2/attributes/atoms/float.py
minfx/neptune_v2/attributes/atoms/git_ref.py
minfx/neptune_v2/attributes/atoms/integer.py
minfx/neptune_v2/attributes/atoms/notebook_ref.py
minfx/neptune_v2/attributes/atoms/run_state.py
minfx/neptune_v2/attributes/atoms/string.py
minfx/neptune_v2/attributes/series/__init__.py
minfx/neptune_v2/attributes/series/fetchable_series.py
minfx/neptune_v2/attributes/series/file_series.py
minfx/neptune_v2/attributes/series/float_series.py
minfx/neptune_v2/attributes/series/series.py
minfx/neptune_v2/attributes/series/string_series.py
minfx/neptune_v2/attributes/sets/__init__.py
minfx/neptune_v2/attributes/sets/set.py
minfx/neptune_v2/attributes/sets/string_set.py
minfx/neptune_v2/cli/__init__.py
minfx/neptune_v2/cli/__main__.py
minfx/neptune_v2/cli/clear.py
minfx/neptune_v2/cli/collect.py
minfx/neptune_v2/cli/commands.py
minfx/neptune_v2/cli/containers.py
minfx/neptune_v2/cli/path_option.py
minfx-0.5.0.dist-info/licenses/LICENSE
minfx-0.5.0.dist-info/METADATA
minfx-0.5.0.dist-info/WHEEL
minfx-0.5.0.dist-info/entry_points.txt
minfx-0.5.0.dist-info/top_level.txt
minfx-0.5.0.dist-info/RECORD
