Metadata-Version: 2.4
Name: minfx
Version: 0.5.0
Summary: A minimal Python package for the minfx project
Author-email: Minfx Team <team@minfx.ai>
Maintainer-email: Minfx Team <team@minfx.ai>
License-Expression: MIT
Project-URL: Homepage, https://github.com/minfx-ai/minfx
Project-URL: Repository, https://github.com/minfx-ai/minfx
Project-URL: Bug Reports, https://github.com/minfx-ai/minfx/issues
Keywords: minfx
Classifier: Development Status :: 3 - Alpha
Classifier: Intended Audience :: Developers
Classifier: Operating System :: OS Independent
Classifier: Programming Language :: Python :: 3
Classifier: Programming Language :: Python :: 3.8
Classifier: Programming Language :: Python :: 3.9
Classifier: Programming Language :: Python :: 3.10
Classifier: Programming Language :: Python :: 3.11
Classifier: Programming Language :: Python :: 3.12
Requires-Python: >=3.8
License-File: LICENSE
Requires-Dist: neptune-scale
Requires-Dist: typing-extensions>=3.10.0
Requires-Dist: six>=1.12.0
Requires-Dist: future>=0.17.1
Requires-Dist: packaging
Requires-Dist: click>=7.0
Requires-Dist: bravado>=11.0.0
Requires-Dist: oauthlib>=2.1.0
Requires-Dist: PyJWT
Requires-Dist: requests>=2.20.0
Requires-Dist: requests-oauthlib>=1.0.0
Requires-Dist: websocket-client!=1.0.0,>=0.35.0
Requires-Dist: urllib3
Requires-Dist: swagger-spec-validator>=2.7.4
Requires-Dist: boto3>=1.28.0
Requires-Dist: Pillow>=1.1.6
Requires-Dist: GitPython>=2.0.8
Requires-Dist: psutil
Requires-Dist: pandas
Provides-Extra: dev
Requires-Dist: pytest>=6.0; extra == "dev"
Requires-Dist: pytest-cov>=2.0; extra == "dev"
Requires-Dist: pytest-mock; extra == "dev"
Requires-Dist: pytest-xdist; extra == "dev"
Requires-Dist: pytest-asyncio; extra == "dev"
Requires-Dist: ruff>=0.8.0; extra == "dev"
Requires-Dist: mypy>=1.0; extra == "dev"
Requires-Dist: mock; extra == "dev"
Requires-Dist: freezegun; extra == "dev"
Requires-Dist: matplotlib; extra == "dev"
Requires-Dist: munch; extra == "dev"
Requires-Dist: moto; extra == "dev"
Requires-Dist: altair; extra == "dev"
Requires-Dist: bokeh; extra == "dev"
Requires-Dist: plotly; extra == "dev"
Requires-Dist: seaborn; extra == "dev"
Requires-Dist: vega_datasets; extra == "dev"
Requires-Dist: torch; extra == "dev"
Requires-Dist: faker; extra == "dev"
Dynamic: license-file
